bvhtoolbox/__init__.py
bvhtoolbox/bvh.py
bvhtoolbox/bvhtransforms.py
bvhtoolbox/bvhtree.py
bvhtoolbox/convert/__init__.py
bvhtoolbox/convert/bvh2csv.py
bvhtoolbox/convert/bvh2csv_batch.py
bvhtoolbox/convert/bvh2egg.py
bvhtoolbox/convert/bvh2egg_batch.py
bvhtoolbox/convert/bvh2xaf.py
bvhtoolbox/convert/bvh2xaf_batch.py
bvhtoolbox/convert/bvh2xaf_helpers.py
bvhtoolbox/convert/bvh2xsf.py
bvhtoolbox/convert/csv2bvh.py
bvhtoolbox/convert/multiprocess.py
bvhtoolbox/convert/prettify_elementtree.py
bvhtoolbox/manipulate/__init__.py
bvhtoolbox/manipulate/offsetjointangles.py
bvhtoolbox/manipulate/removeframes.py
bvhtoolbox/manipulate/renamejoints.py
bvhtoolbox-0.1.3.dist-info/LICENSE
bvhtoolbox-0.1.3.dist-info/METADATA
bvhtoolbox-0.1.3.dist-info/WHEEL
bvhtoolbox-0.1.3.dist-info/entry_points.txt
bvhtoolbox-0.1.3.dist-info/top_level.txt
bvhtoolbox-0.1.3.dist-info/RECORD
