Metadata-Version: 2.1
Name: bvhtoolbox
Version: 0.1.3
Summary: Python module for reading, manipulating and converting BVH motion capture files.
Home-page: https://github.com/olafhaag/bvh-toolbox
Author: Olaf Haag
Author-email: contact@olafhaag.com
License: UNKNOWN
Project-URL: Bug Reports, https://github.com/olafhaag/bvh-toolbox/issues
Project-URL: Source, https://github.com/olafhaag/bvh-toolbox/
Keywords: bvh BioVision mocap motion-capture convert animation 3d
Platform: UNKNOWN
Classifier: License :: OSI Approved :: MIT License
Classifier: Programming Language :: Python :: 3
Classifier: Operating System :: OS Independent
Classifier: Environment :: Console
Classifier: Development Status :: 3 - Alpha
Requires-Python: >=3
Requires-Dist: numpy
Requires-Dist: transforms3d (>=0.3.1)
Provides-Extra: dev
Requires-Dist: sympy ; extra == 'dev'
Requires-Dist: panda3d ; extra == 'dev'
Requires-Dist: twine ; extra == 'dev'
Provides-Extra: test
Requires-Dist: pytest ; extra == 'test'
Requires-Dist: hypothesis ; extra == 'test'
